faissdb/__init__.py
faissdb/config.py
faissdb/faissdb.py
faissdb/faisskv.py
faissdb/indexer.py
faissdb/utility.py
faissdb-1.0.0.1.dist-info/METADATA
faissdb-1.0.0.1.dist-info/WHEEL
faissdb-1.0.0.1.dist-info/top_level.txt
faissdb-1.0.0.1.dist-info/RECORD
